<?xml version="1.0" encoding="UTF-8"?>
<beans xmlns="http://www.springframework.org/schema/beans"
	xmlns:xsi="http://www.w3.org/2001/XMLSchema-instance" xmlns:osgi="http://www.springframework.org/schema/osgi"
	xmlns:context="http://www.springframework.org/schema/context"
	xmlns:mvc="http://www.springframework.org/schema/mvc"
	xsi:schemaLocation="http://www.springframework.org/schema/beans
	http://www.springframework.org/schema/beans/spring-beans.xsd   
	http://www.springframework.org/schema/osgi
	http://www.springframework.org/schema/osgi/spring-osgi.xsd
	http://www.springframework.org/schema/context 
	http://www.springframework.org/schema/context/spring-context.xsd">
    
	<!-- promethues -->
    <bean name="promethuesInit" init-method="init" class="com.tl.promethues.PromethuesInit"></bean>
    <!-- 
    <bean name="promethuesAllDayUtil" init-method="run" class="com.tl.promethues.PromethuesAllDayUtil">
    <property name="time" value="00:00:00"></property>
    </bean> -->
    <bean name="promethuesUtil" init-method="run" class="com.tl.promethues.PromethuesAllDayUtil">
    	<property name="time" value="00:00:00"></property>
    </bean>
    
</beans>